openmc_plotter/__init__.py
openmc_plotter/__main__.py
openmc_plotter/custom_widgets.py
openmc_plotter/docks.py
openmc_plotter/main_window.py
openmc_plotter/overlays.py
openmc_plotter/plot_colors.py
openmc_plotter/plotgui.py
openmc_plotter/plotmodel.py
openmc_plotter/scientific_spin_box.py
openmc_plotter/statepointmodel.py
openmc_plotter/tools.py
openmc_plotter/assets/openmc_logo.png
openmc_plotter/assets/splash.png
openmc_plotter-0.4.0.dist-info/LICENSE
openmc_plotter-0.4.0.dist-info/METADATA
openmc_plotter-0.4.0.dist-info/WHEEL
openmc_plotter-0.4.0.dist-info/entry_points.txt
openmc_plotter-0.4.0.dist-info/top_level.txt
openmc_plotter-0.4.0.dist-info/RECORD
