Metadata-Version: 2.1
Name: openmc-plotter
Version: 0.4.0
Summary: Plotting tool for OpenMC models and tally data
Home-page: https://github.com/openmc-dev/plotter
Download-URL: https://github.com/openmc-dev/plotter
Author: OpenMC Development Team
Author-email: openmc@anl.gov
Project-URL: Issue Tracker, https://github.com/openmc-dev/plotter/issues
Project-URL: Source Code, https://github.com/openmc-dev/plotter
Classifier: Development Status :: 4 - Beta
Classifier: Intended Audience :: Developers
Classifier: Intended Audience :: End Users/Desktop
Classifier: Intended Audience :: Science/Research
Classifier: Natural Language :: English
Classifier: Topic :: Scientific/Engineering
Classifier: Programming Language :: Python :: 3
Classifier: Programming Language :: Python :: 3.6
Classifier: Programming Language :: Python :: 3.7
Classifier: Programming Language :: Python :: 3.8
Classifier: Programming Language :: Python :: 3.9
Classifier: Programming Language :: Python :: 3.10
Classifier: Programming Language :: Python :: 3.11
Requires-Python: >=3.6
License-File: LICENSE
Requires-Dist: openmc >0.12.2
Requires-Dist: numpy
Requires-Dist: matplotlib
Requires-Dist: PySide6
Provides-Extra: test
Requires-Dist: pytest ; extra == 'test'
Requires-Dist: pytest-qt ; extra == 'test'
Provides-Extra: vtk
Requires-Dist: vtk ; extra == 'vtk'
